ConTextMining/ConTextMining.py
ConTextMining/__init__.py
ConTextMining-0.0.6.dist-info/LICENSE.txt
ConTextMining-0.0.6.dist-info/METADATA
ConTextMining-0.0.6.dist-info/WHEEL
ConTextMining-0.0.6.dist-info/top_level.txt
ConTextMining-0.0.6.dist-info/RECORD
