Metadata-Version: 2.1
Name: ConTextMining
Version: 0.0.6
Summary: Complementing topic models with few-shot in-context learning to generate interpretable topics
Author: Charles Alba
Author-email: alba@wustl.edu
Keywords: generative AI,text mining,topic modeling,LLMs
Classifier: Development Status :: 1 - Planning
Classifier: Intended Audience :: Education
Classifier: Intended Audience :: Science/Research
Classifier: Programming Language :: Python :: 3
Classifier: Operating System :: Unix
Classifier: Operating System :: MacOS :: MacOS X
Classifier: Operating System :: Microsoft :: Windows
License-File: LICENSE.txt
Requires-Dist: torch
Requires-Dist: transformers
Requires-Dist: tokenizers
Requires-Dist: huggingface-hub
Requires-Dist: accelerate
